peakventures/__init__.py
peakventures/api.py
peakventures/conversions.py
peakventures/credentials.py
peakventures/storage.py
peakventures-1.2.8.dist-info/WHEEL
peakventures-1.2.8.dist-info/METADATA
peakventures-1.2.8.dist-info/RECORD
