Metadata-Version: 2.1
Name: peakventures
Version: 1.2.8
Summary: PeakVentures Python Utilities
Author: Volodymyr Smirnov
Author-email: volodymyr@peakventures.co
Requires-Python: >=3.8,<4.0
Classifier: Programming Language :: Python :: 3
Classifier: Programming Language :: Python :: 3.8
Classifier: Programming Language :: Python :: 3.9
Classifier: Programming Language :: Python :: 3.10
Classifier: Programming Language :: Python :: 3.11
Requires-Dist: boto3 (>=1.28.11,<2.0.0)
Requires-Dist: requests (>=2.31.0,<3.0.0)
Requires-Dist: tenacity (>=8.2.2,<9.0.0)
Requires-Dist: websockets (>=11.0.3,<12.0.0)
